gooddata_pipelines/__init__.py
gooddata_pipelines/_version.py
gooddata_pipelines/py.typed
gooddata_pipelines/api/__init__.py
gooddata_pipelines/api/gooddata_api.py
gooddata_pipelines/api/gooddata_api_wrapper.py
gooddata_pipelines/backup_and_restore/__init__.py
gooddata_pipelines/backup_and_restore/backup_input_processor.py
gooddata_pipelines/backup_and_restore/backup_manager.py
gooddata_pipelines/backup_and_restore/base_manager.py
gooddata_pipelines/backup_and_restore/constants.py
gooddata_pipelines/backup_and_restore/csv_reader.py
gooddata_pipelines/backup_and_restore/restore_manager.py
gooddata_pipelines/backup_and_restore/models/__init__.py
gooddata_pipelines/backup_and_restore/models/input_type.py
gooddata_pipelines/backup_and_restore/models/storage.py
gooddata_pipelines/backup_and_restore/models/workspace_response.py
gooddata_pipelines/backup_and_restore/storage/__init__.py
gooddata_pipelines/backup_and_restore/storage/azure_storage.py
gooddata_pipelines/backup_and_restore/storage/base_storage.py
gooddata_pipelines/backup_and_restore/storage/local_storage.py
gooddata_pipelines/backup_and_restore/storage/s3_storage.py
gooddata_pipelines/ldm_extension/__init__.py
gooddata_pipelines/ldm_extension/input_processor.py
gooddata_pipelines/ldm_extension/input_validator.py
gooddata_pipelines/ldm_extension/ldm_extension_manager.py
gooddata_pipelines/ldm_extension/models/__init__.py
gooddata_pipelines/ldm_extension/models/aliases.py
gooddata_pipelines/ldm_extension/models/analytical_object.py
gooddata_pipelines/ldm_extension/models/custom_data_object.py
gooddata_pipelines/logger/__init__.py
gooddata_pipelines/logger/logger.py
gooddata_pipelines/provisioning/__init__.py
gooddata_pipelines/provisioning/provisioning.py
gooddata_pipelines/provisioning/assets/wdf_setting.json
gooddata_pipelines/provisioning/entities/__init__.py
gooddata_pipelines/provisioning/entities/user_data_filters/__init__.py
gooddata_pipelines/provisioning/entities/user_data_filters/user_data_filters.py
gooddata_pipelines-1.58.0.dist-info/METADATA
gooddata_pipelines-1.58.0.dist-info/WHEEL
gooddata_pipelines-1.58.0.dist-info/licenses/LICENSE.txt
gooddata_pipelines-1.58.0.dist-info/RECORD
