Metadata-Version: 2.4
Name: gooddata-pipelines
Version: 1.58.0
Summary: GoodData Cloud lifecycle automation pipelines
Author-email: GoodData <support@gooddata.com>
License-Expression: MIT
License-File: LICENSE.txt
Requires-Python: >=3.10
Requires-Dist: azure-identity<2.0.0,>=1.15.0
Requires-Dist: azure-storage-blob<13.0.0,>=12.19.0
Requires-Dist: boto3-stubs<2.0.0,>=1.39.3
Requires-Dist: boto3<2.0.0,>=1.39.3
Requires-Dist: gooddata-sdk~=1.58.0
Requires-Dist: pydantic<3.0.0,>=2.9.2
Requires-Dist: requests<3.0.0,>=2.32.3
Requires-Dist: types-pyyaml<7.0.0,>=6.0.12.20250326
Requires-Dist: types-requests<3.0.0,>1.0.0
